setup.py
emoticry/__init__.py
emoticry/emoticry.py
emoticry/main.py
emoticry.egg-info/PKG-INFO
emoticry.egg-info/SOURCES.txt
emoticry.egg-info/dependency_links.txt
emoticry.egg-info/entry_points.txt
emoticry.egg-info/not-zip-safe
emoticry.egg-info/top_level.txt