Metadata-Version: 1.1
Name: emoticry
Version: 0.0.6
Summary: Mercilessly translates file names to emoji
Home-page: https://github.com/saxbophone/emoticry
Author: Joshua Saxby
Author-email: joshua.a.saxby@gmail.com
License: MIT
Keywords: emoji files hack deface joke
Platform: UNKNOWN
Classifier: Development Status :: 3 - Alpha
Classifier: Intended Audience :: Developers
Classifier: Intended Audience :: Education
Classifier: Intended Audience :: System Administrators
Classifier: Topic :: Artistic Software
Classifier: Topic :: Education
Classifier: License :: OSI Approved :: MIT License
Classifier: Programming Language :: Python :: 2.7
